callsigns/__init__.py
callsigns/builder.py
callsigns/constants.py
callsigns/fetcher.py
callsigns/parser.py
callsigns/py.typed
callsigns/uploader.py
callsigns-0.0.1.dist-info/LICENSE
callsigns-0.0.1.dist-info/METADATA
callsigns-0.0.1.dist-info/WHEEL
callsigns-0.0.1.dist-info/top_level.txt
callsigns-0.0.1.dist-info/RECORD
